{
    "switches": {},
    "tag groups": {
        "additional_attributes": [],
        "environment": [
            "urban"
        ],
        "light": [
            "auto_bright_dark",
            "dark",
            "natural"
        ],
        "time_of_day": [
            "twilight"
        ],
        "track_layout": [
            "straight"
        ],
        "weather": [
            "cloudy"
        ]
    },
    "tracks": {
        "0": {
            "left rail": {
                "points": [
                    {
                        "x": 890,
                        "y": 1079
                    },
                    {
                        "x": 899,
                        "y": 712
                    },
                    {
                        "x": 902,
                        "y": 609
                    },
                    {
                        "x": 904,
                        "y": 547
                    },
                    {
                        "x": 905,
                        "y": 509
                    },
                    {
                        "x": 906,
                        "y": 490
                    },
                    {
                        "x": 908,
                        "y": 477
                    }
                ]
            },
            "relative position": "ego",
            "right rail": {
                "points": [
                    {
                        "x": 1217,
                        "y": 1081
                    },
                    {
                        "x": 1031,
                        "y": 712
                    },
                    {
                        "x": 981,
                        "y": 609
                    },
                    {
                        "x": 950,
                        "y": 547
                    },
                    {
                        "x": 930,
                        "y": 509
                    },
                    {
                        "x": 921,
                        "y": 490
                    },
                    {
                        "x": 917,
                        "y": 477
                    }
                ]
            }
        },
        "1": {
            "left rail": {
                "points": [
                    {
                        "x": 2,
                        "y": 1077
                    },
                    {
                        "x": 176,
                        "y": 953
                    },
                    {
                        "x": 389,
                        "y": 809
                    },
                    {
                        "x": 659,
                        "y": 624
                    },
                    {
                        "x": 759,
                        "y": 561
                    },
                    {
                        "x": 816,
                        "y": 521
                    },
                    {
                        "x": 845,
                        "y": 504
                    },
                    {
                        "x": 869,
                        "y": 487
                    }
                ]
            },
            "relative position": "left",
            "right rail": {
                "points": [
                    {
                        "x": 308,
                        "y": 1079
                    },
                    {
                        "x": 424,
                        "y": 954
                    },
                    {
                        "x": 563,
                        "y": 809
                    },
                    {
                        "x": 746,
                        "y": 624
                    },
                    {
                        "x": 809,
                        "y": 561
                    },
                    {
                        "x": 847,
                        "y": 521
                    },
                    {
                        "x": 865,
                        "y": 504
                    },
                    {
                        "x": 883,
                        "y": 487
                    }
                ]
            }
        }
    }
}