{
    "switches": {},
    "tag groups": {
        "additional_attributes": [],
        "environment": [
            "urban",
            "station"
        ],
        "light": [
            "auto_bright_dark",
            "natural"
        ],
        "time_of_day": [
            "twilight"
        ],
        "track_layout": [
            "curve"
        ],
        "weather": [
            "cloudy"
        ]
    },
    "tracks": {
        "0": {
            "left rail": {
                "points": [
                    {
                        "x": 888,
                        "y": 1078
                    },
                    {
                        "x": 892,
                        "y": 920
                    },
                    {
                        "x": 898,
                        "y": 769
                    },
                    {
                        "x": 901,
                        "y": 700
                    },
                    {
                        "x": 904,
                        "y": 651
                    },
                    {
                        "x": 911,
                        "y": 605
                    },
                    {
                        "x": 918,
                        "y": 581
                    },
                    {
                        "x": 926,
                        "y": 563
                    },
                    {
                        "x": 938,
                        "y": 544
                    },
                    {
                        "x": 957,
                        "y": 526
                    },
                    {
                        "x": 972,
                        "y": 517
                    },
                    {
                        "x": 989,
                        "y": 509
                    },
                    {
                        "x": 1012,
                        "y": 498
                    },
                    {
                        "x": 1029,
                        "y": 491
                    }
                ]
            },
            "relative position": "ego",
            "right rail": {
                "points": [
                    {
                        "x": 1216,
                        "y": 1080
                    },
                    {
                        "x": 1136,
                        "y": 921
                    },
                    {
                        "x": 1062,
                        "y": 769
                    },
                    {
                        "x": 1030,
                        "y": 700
                    },
                    {
                        "x": 1007,
                        "y": 651
                    },
                    {
                        "x": 989,
                        "y": 605
                    },
                    {
                        "x": 983,
                        "y": 581
                    },
                    {
                        "x": 982,
                        "y": 563
                    },
                    {
                        "x": 985,
                        "y": 544
                    },
                    {
                        "x": 995,
                        "y": 526
                    },
                    {
                        "x": 1003,
                        "y": 517
                    },
                    {
                        "x": 1016,
                        "y": 509
                    },
                    {
                        "x": 1036,
                        "y": 498
                    },
                    {
                        "x": 1047,
                        "y": 491
                    }
                ]
            }
        }
    }
}