{
    "switches": {},
    "tag groups": {
        "additional_attributes": [],
        "environment": [
            "rural"
        ],
        "light": [
            "auto_bright_dark",
            "hard shadows",
            "natural"
        ],
        "time_of_day": [
            "day"
        ],
        "track_layout": [
            "curve"
        ],
        "weather": [
            "cloudy"
        ]
    },
    "tracks": {
        "0": {
            "left rail": {
                "points": [
                    {
                        "x": 892,
                        "y": 1078
                    },
                    {
                        "x": 901,
                        "y": 649
                    },
                    {
                        "x": 904,
                        "y": 535
                    },
                    {
                        "x": 904,
                        "y": 504
                    },
                    {
                        "x": 890,
                        "y": 494
                    }
                ]
            },
            "relative position": "ego",
            "right rail": {
                "points": [
                    {
                        "x": 1216,
                        "y": 1078
                    },
                    {
                        "x": 987,
                        "y": 622
                    },
                    {
                        "x": 939,
                        "y": 528
                    },
                    {
                        "x": 927,
                        "y": 506
                    },
                    {
                        "x": 917,
                        "y": 497
                    },
                    {
                        "x": 895,
                        "y": 490
                    }
                ]
            }
        }
    }
}