{
    "switches": {},
    "tag groups": {
        "additional_attributes": [],
        "environment": [
            "rural"
        ],
        "light": [
            "auto_bright_dark",
            "natural",
            "uniform",
            "bright"
        ],
        "time_of_day": [
            "day"
        ],
        "track_layout": [
            "curve"
        ],
        "weather": [
            "cloudy",
            "snow"
        ]
    },
    "tracks": {
        "0": {
            "left rail": {
                "points": [
                    {
                        "x": 889,
                        "y": 1076
                    },
                    {
                        "x": 896,
                        "y": 824
                    },
                    {
                        "x": 901,
                        "y": 651
                    },
                    {
                        "x": 904,
                        "y": 562
                    },
                    {
                        "x": 905,
                        "y": 515
                    },
                    {
                        "x": 906,
                        "y": 496
                    },
                    {
                        "x": 911,
                        "y": 489
                    },
                    {
                        "x": 928,
                        "y": 484
                    },
                    {
                        "x": 948,
                        "y": 481
                    },
                    {
                        "x": 987,
                        "y": 477
                    }
                ]
            },
            "relative position": "ego",
            "right rail": {
                "points": [
                    {
                        "x": 1215,
                        "y": 1077
                    },
                    {
                        "x": 1094,
                        "y": 834
                    },
                    {
                        "x": 1006,
                        "y": 656
                    },
                    {
                        "x": 962,
                        "y": 567
                    },
                    {
                        "x": 935,
                        "y": 516
                    },
                    {
                        "x": 927,
                        "y": 499
                    },
                    {
                        "x": 927,
                        "y": 490
                    },
                    {
                        "x": 935,
                        "y": 486
                    },
                    {
                        "x": 952,
                        "y": 483
                    },
                    {
                        "x": 986,
                        "y": 479
                    }
                ]
            }
        }
    }
}