{
    "switches": {},
    "tag groups": {
        "additional_attributes": [],
        "environment": [
            "rural"
        ],
        "light": [
            "hard shadows",
            "natural",
            "auto_bright_dark"
        ],
        "time_of_day": [
            "day"
        ],
        "track_layout": [
            "curve"
        ],
        "weather": [
            "sunny",
            "snow"
        ]
    },
    "tracks": {
        "0": {
            "left rail": {
                "points": [
                    {
                        "x": 945,
                        "y": 1085
                    },
                    {
                        "x": 952,
                        "y": 913
                    },
                    {
                        "x": 961,
                        "y": 793
                    },
                    {
                        "x": 977,
                        "y": 672
                    },
                    {
                        "x": 999,
                        "y": 600
                    },
                    {
                        "x": 1023,
                        "y": 559
                    },
                    {
                        "x": 1051,
                        "y": 533
                    },
                    {
                        "x": 1093,
                        "y": 506
                    },
                    {
                        "x": 1125,
                        "y": 495
                    },
                    {
                        "x": 1160,
                        "y": 485
                    }
                ]
            },
            "relative position": "ego",
            "right rail": {
                "points": [
                    {
                        "x": 1272,
                        "y": 1087
                    },
                    {
                        "x": 1186,
                        "y": 905
                    },
                    {
                        "x": 1135,
                        "y": 790
                    },
                    {
                        "x": 1088,
                        "y": 671
                    },
                    {
                        "x": 1075,
                        "y": 600
                    },
                    {
                        "x": 1075,
                        "y": 564
                    },
                    {
                        "x": 1087,
                        "y": 544
                    },
                    {
                        "x": 1108,
                        "y": 520
                    },
                    {
                        "x": 1132,
                        "y": 504
                    },
                    {
                        "x": 1169,
                        "y": 489
                    }
                ]
            }
        }
    }
}