{
    "switches": {},
    "tag groups": {
        "additional_attributes": [],
        "environment": [
            "rural",
            "urban"
        ],
        "light": [
            "auto_bright_dark",
            "natural",
            "uniform",
            "bright"
        ],
        "time_of_day": [
            "day"
        ],
        "track_layout": [
            "curve"
        ],
        "weather": [
            "sunny"
        ]
    },
    "tracks": {
        "0": {
            "left rail": {
                "points": [
                    {
                        "x": 891,
                        "y": 1085
                    },
                    {
                        "x": 899,
                        "y": 768
                    },
                    {
                        "x": 902,
                        "y": 612
                    },
                    {
                        "x": 904,
                        "y": 567
                    },
                    {
                        "x": 905,
                        "y": 542
                    },
                    {
                        "x": 910,
                        "y": 519
                    },
                    {
                        "x": 922,
                        "y": 500
                    },
                    {
                        "x": 940,
                        "y": 489
                    },
                    {
                        "x": 961,
                        "y": 481
                    }
                ]
            },
            "relative position": "ego",
            "right rail": {
                "points": [
                    {
                        "x": 1223,
                        "y": 1087
                    },
                    {
                        "x": 1059,
                        "y": 759
                    },
                    {
                        "x": 981,
                        "y": 608
                    },
                    {
                        "x": 963,
                        "y": 571
                    },
                    {
                        "x": 950,
                        "y": 541
                    },
                    {
                        "x": 944,
                        "y": 520
                    },
                    {
                        "x": 946,
                        "y": 500
                    },
                    {
                        "x": 954,
                        "y": 492
                    },
                    {
                        "x": 970,
                        "y": 483
                    }
                ]
            }
        }
    }
}