{
    "switches": {
        "0": {
            "direction": "unknown",
            "kind": "merge",
            "marks": [
                {
                    "x": 856,
                    "y": 470
                },
                {
                    "x": 868,
                    "y": 472
                }
            ],
            "track_ids": [
                1,
                2
            ]
        }
    },
    "tag groups": {
        "additional_attributes": [],
        "environment": [
            "urban",
            "station"
        ],
        "light": [
            "auto_bright_dark",
            "uniform",
            "natural"
        ],
        "time_of_day": [
            "day"
        ],
        "track_layout": [
            "straight"
        ],
        "weather": [
            "cloudy",
            "snow"
        ]
    },
    "tracks": {
        "0": {
            "left rail": {
                "points": [
                    {
                        "x": 875,
                        "y": 1075
                    },
                    {
                        "x": 889,
                        "y": 710
                    },
                    {
                        "x": 895,
                        "y": 545
                    },
                    {
                        "x": 900,
                        "y": 466
                    }
                ]
            },
            "relative position": "ego",
            "right rail": {
                "points": [
                    {
                        "x": 1203,
                        "y": 1075
                    },
                    {
                        "x": 1026,
                        "y": 713
                    },
                    {
                        "x": 943,
                        "y": 543
                    },
                    {
                        "x": 908,
                        "y": 465
                    }
                ]
            }
        },
        "1": {
            "left rail": {
                "points": [
                    {
                        "x": 4,
                        "y": 896
                    },
                    {
                        "x": 2,
                        "y": 896
                    },
                    {
                        "x": 317,
                        "y": 740
                    },
                    {
                        "x": 427,
                        "y": 689
                    },
                    {
                        "x": 534,
                        "y": 635
                    },
                    {
                        "x": 694,
                        "y": 556
                    },
                    {
                        "x": 768,
                        "y": 516
                    },
                    {
                        "x": 802,
                        "y": 499
                    },
                    {
                        "x": 861,
                        "y": 470
                    }
                ]
            },
            "relative position": "left",
            "right rail": {
                "points": [
                    {
                        "x": 4,
                        "y": 1044
                    },
                    {
                        "x": 317,
                        "y": 836
                    },
                    {
                        "x": 416,
                        "y": 770
                    },
                    {
                        "x": 566,
                        "y": 673
                    },
                    {
                        "x": 734,
                        "y": 563
                    },
                    {
                        "x": 810,
                        "y": 510
                    },
                    {
                        "x": 836,
                        "y": 492
                    },
                    {
                        "x": 869,
                        "y": 470
                    }
                ]
            }
        },
        "2": {
            "left rail": {
                "points": [
                    {
                        "x": 0,
                        "y": 596
                    },
                    {
                        "x": 308,
                        "y": 544
                    },
                    {
                        "x": 418,
                        "y": 527
                    },
                    {
                        "x": 491,
                        "y": 516
                    },
                    {
                        "x": 534,
                        "y": 508
                    },
                    {
                        "x": 622,
                        "y": 497
                    },
                    {
                        "x": 676,
                        "y": 489
                    },
                    {
                        "x": 725,
                        "y": 484
                    },
                    {
                        "x": 744,
                        "y": 483
                    },
                    {
                        "x": 733,
                        "y": 483
                    },
                    {
                        "x": 737,
                        "y": 482
                    },
                    {
                        "x": 853,
                        "y": 472
                    },
                    {
                        "x": 901,
                        "y": 464
                    }
                ]
            },
            "relative position": "left",
            "right rail": {
                "points": [
                    {
                        "x": 0,
                        "y": 637
                    },
                    {
                        "x": 263,
                        "y": 582
                    },
                    {
                        "x": 527,
                        "y": 531
                    },
                    {
                        "x": 750,
                        "y": 484
                    },
                    {
                        "x": 853,
                        "y": 472
                    },
                    {
                        "x": 901,
                        "y": 464
                    }
                ]
            }
        }
    }
}