{
    "switches": {},
    "tag groups": {
        "additional_attributes": [],
        "environment": [
            "rural"
        ],
        "light": [
            "auto_bright_dark",
            "uniform",
            "natural"
        ],
        "time_of_day": [
            "day"
        ],
        "track_layout": [
            "curve"
        ],
        "weather": [
            "cloudy",
            "rainy",
            "snow"
        ]
    },
    "tracks": {
        "0": {
            "left rail": {
                "points": [
                    {
                        "x": 681,
                        "y": 465
                    },
                    {
                        "x": 680,
                        "y": 465
                    },
                    {
                        "x": 744,
                        "y": 508
                    },
                    {
                        "x": 769,
                        "y": 537
                    },
                    {
                        "x": 790,
                        "y": 587
                    },
                    {
                        "x": 804,
                        "y": 653
                    },
                    {
                        "x": 813,
                        "y": 780
                    },
                    {
                        "x": 812,
                        "y": 872
                    },
                    {
                        "x": 808,
                        "y": 1074
                    },
                    {
                        "x": 808,
                        "y": 1075
                    }
                ]
            },
            "relative position": "ego",
            "right rail": {
                "points": [
                    {
                        "x": 699,
                        "y": 465
                    },
                    {
                        "x": 698,
                        "y": 465
                    },
                    {
                        "x": 779,
                        "y": 508
                    },
                    {
                        "x": 817,
                        "y": 537
                    },
                    {
                        "x": 865,
                        "y": 587
                    },
                    {
                        "x": 913,
                        "y": 653
                    },
                    {
                        "x": 988,
                        "y": 781
                    },
                    {
                        "x": 1035,
                        "y": 873
                    },
                    {
                        "x": 1139,
                        "y": 1077
                    },
                    {
                        "x": 1139,
                        "y": 1078
                    }
                ]
            }
        }
    }
}