{
    "switches": {},
    "tag groups": {
        "additional_attributes": [],
        "environment": [
            "rural",
            "urban"
        ],
        "light": [
            "natural",
            "auto_bright_dark",
            "uniform"
        ],
        "time_of_day": [
            "day"
        ],
        "track_layout": [
            "curve",
            "straight"
        ],
        "weather": [
            "cloudy"
        ]
    },
    "tracks": {
        "0": {
            "left rail": {
                "points": [
                    {
                        "x": 1029,
                        "y": 485
                    },
                    {
                        "x": 1028,
                        "y": 486
                    },
                    {
                        "x": 1026,
                        "y": 496
                    },
                    {
                        "x": 1019,
                        "y": 519
                    },
                    {
                        "x": 1004,
                        "y": 564
                    },
                    {
                        "x": 989,
                        "y": 641
                    },
                    {
                        "x": 977,
                        "y": 756
                    },
                    {
                        "x": 970,
                        "y": 875
                    },
                    {
                        "x": 965,
                        "y": 1077
                    },
                    {
                        "x": 965,
                        "y": 1078
                    }
                ]
            },
            "relative position": "ego",
            "right rail": {
                "points": [
                    {
                        "x": 1041,
                        "y": 485
                    },
                    {
                        "x": 1041,
                        "y": 486
                    },
                    {
                        "x": 1042,
                        "y": 496
                    },
                    {
                        "x": 1047,
                        "y": 519
                    },
                    {
                        "x": 1057,
                        "y": 564
                    },
                    {
                        "x": 1082,
                        "y": 641
                    },
                    {
                        "x": 1132,
                        "y": 757
                    },
                    {
                        "x": 1188,
                        "y": 876
                    },
                    {
                        "x": 1290,
                        "y": 1079
                    },
                    {
                        "x": 1290,
                        "y": 1080
                    }
                ]
            }
        },
        "1": {
            "left rail": {
                "points": [
                    {
                        "x": 1108,
                        "y": 497
                    },
                    {
                        "x": 1120,
                        "y": 502
                    },
                    {
                        "x": 1141,
                        "y": 512
                    },
                    {
                        "x": 1206,
                        "y": 542
                    },
                    {
                        "x": 1278,
                        "y": 575
                    },
                    {
                        "x": 1358,
                        "y": 611
                    },
                    {
                        "x": 1493,
                        "y": 675
                    },
                    {
                        "x": 1644,
                        "y": 744
                    },
                    {
                        "x": 1908,
                        "y": 865
                    },
                    {
                        "x": 1908,
                        "y": 866
                    }
                ]
            },
            "relative position": "right",
            "right rail": {
                "points": [
                    {
                        "x": 1129,
                        "y": 497
                    },
                    {
                        "x": 1143,
                        "y": 502
                    },
                    {
                        "x": 1169,
                        "y": 512
                    },
                    {
                        "x": 1254,
                        "y": 542
                    },
                    {
                        "x": 1344,
                        "y": 575
                    },
                    {
                        "x": 1443,
                        "y": 611
                    },
                    {
                        "x": 1620,
                        "y": 675
                    },
                    {
                        "x": 1809,
                        "y": 745
                    },
                    {
                        "x": 2140,
                        "y": 866
                    },
                    {
                        "x": 2140,
                        "y": 867
                    }
                ]
            }
        },
        "2": {
            "left rail": {
                "points": [
                    {
                        "x": 1154,
                        "y": 495
                    },
                    {
                        "x": 1185,
                        "y": 501
                    },
                    {
                        "x": 1280,
                        "y": 524
                    },
                    {
                        "x": 1436,
                        "y": 563
                    },
                    {
                        "x": 1621,
                        "y": 610
                    },
                    {
                        "x": 1911,
                        "y": 681
                    },
                    {
                        "x": 1911,
                        "y": 682
                    }
                ]
            },
            "relative position": "right",
            "right rail": {
                "points": [
                    {
                        "x": 1177,
                        "y": 495
                    },
                    {
                        "x": 1211,
                        "y": 501
                    },
                    {
                        "x": 1319,
                        "y": 524
                    },
                    {
                        "x": 1496,
                        "y": 563
                    },
                    {
                        "x": 1707,
                        "y": 610
                    },
                    {
                        "x": 2036,
                        "y": 681
                    },
                    {
                        "x": 2036,
                        "y": 682
                    }
                ]
            }
        }
    }
}