{
    "switches": {},
    "tag groups": {
        "additional_attributes": [],
        "environment": [
            "rural"
        ],
        "light": [
            "natural",
            "auto_bright_dark",
            "uniform"
        ],
        "time_of_day": [
            "day"
        ],
        "track_layout": [
            "curve"
        ],
        "weather": [
            "cloudy"
        ]
    },
    "tracks": {
        "0": {
            "left rail": {
                "points": [
                    {
                        "x": 922,
                        "y": 1081
                    },
                    {
                        "x": 936,
                        "y": 782
                    },
                    {
                        "x": 964,
                        "y": 614
                    },
                    {
                        "x": 1008,
                        "y": 555
                    },
                    {
                        "x": 1059,
                        "y": 529
                    },
                    {
                        "x": 1099,
                        "y": 517
                    }
                ]
            },
            "relative position": "ego",
            "right rail": {
                "points": [
                    {
                        "x": 1240,
                        "y": 1078
                    },
                    {
                        "x": 1099,
                        "y": 782
                    },
                    {
                        "x": 1041,
                        "y": 614
                    },
                    {
                        "x": 1056,
                        "y": 555
                    },
                    {
                        "x": 1095,
                        "y": 529
                    },
                    {
                        "x": 1128,
                        "y": 517
                    }
                ]
            }
        }
    }
}