{
    "switches": {},
    "tag groups": {
        "additional_attributes": [],
        "environment": [
            "rural"
        ],
        "light": [
            "natural",
            "auto_bright_dark",
            "uniform"
        ],
        "time_of_day": [
            "day"
        ],
        "track_layout": [
            "straight"
        ],
        "weather": [
            "cloudy"
        ]
    },
    "tracks": {
        "0": {
            "left rail": {
                "points": [
                    {
                        "x": 889,
                        "y": 1080
                    },
                    {
                        "x": 894,
                        "y": 849
                    },
                    {
                        "x": 900,
                        "y": 649
                    },
                    {
                        "x": 904,
                        "y": 544
                    },
                    {
                        "x": 905,
                        "y": 500
                    },
                    {
                        "x": 906,
                        "y": 477
                    }
                ]
            },
            "relative position": "ego",
            "right rail": {
                "points": [
                    {
                        "x": 1210,
                        "y": 1078
                    },
                    {
                        "x": 1096,
                        "y": 850
                    },
                    {
                        "x": 996,
                        "y": 649
                    },
                    {
                        "x": 945,
                        "y": 544
                    },
                    {
                        "x": 926,
                        "y": 500
                    },
                    {
                        "x": 916,
                        "y": 477
                    }
                ]
            }
        }
    }
}