{
    "switches": {},
    "tag groups": {
        "additional_attributes": [],
        "environment": [
            "rural"
        ],
        "light": [
            "natural",
            "auto_bright_dark",
            "uniform"
        ],
        "time_of_day": [
            "day"
        ],
        "track_layout": [
            "curve"
        ],
        "weather": [
            "cloudy"
        ]
    },
    "tracks": {
        "0": {
            "left rail": {
                "points": [
                    {
                        "x": 953,
                        "y": 499
                    },
                    {
                        "x": 951,
                        "y": 500
                    },
                    {
                        "x": 944,
                        "y": 510
                    },
                    {
                        "x": 932,
                        "y": 535
                    },
                    {
                        "x": 924,
                        "y": 574
                    },
                    {
                        "x": 918,
                        "y": 642
                    },
                    {
                        "x": 911,
                        "y": 787
                    },
                    {
                        "x": 903,
                        "y": 1079
                    },
                    {
                        "x": 903,
                        "y": 1080
                    }
                ]
            },
            "relative position": "ego",
            "right rail": {
                "points": [
                    {
                        "x": 968,
                        "y": 499
                    },
                    {
                        "x": 967,
                        "y": 500
                    },
                    {
                        "x": 963,
                        "y": 510
                    },
                    {
                        "x": 965,
                        "y": 535
                    },
                    {
                        "x": 978,
                        "y": 574
                    },
                    {
                        "x": 1008,
                        "y": 642
                    },
                    {
                        "x": 1078,
                        "y": 788
                    },
                    {
                        "x": 1222,
                        "y": 1081
                    },
                    {
                        "x": 1222,
                        "y": 1082
                    }
                ]
            }
        }
    }
}